apter/__init__.py
apter/apter.py
apter-0.10.dist-info/LICENSE.txt
apter-0.10.dist-info/METADATA
apter-0.10.dist-info/WHEEL
apter-0.10.dist-info/top_level.txt
apter-0.10.dist-info/RECORD
